api_requests.py
config.py
exceptions.py
main.py
weatherstack_mcp_server-0.1.1.dist-info/METADATA
weatherstack_mcp_server-0.1.1.dist-info/WHEEL
weatherstack_mcp_server-0.1.1.dist-info/entry_points.txt
weatherstack_mcp_server-0.1.1.dist-info/licenses/LICENSE
weatherstack_mcp_server-0.1.1.dist-info/RECORD
